{"code": "platelets", "name": "Plats", "readings": [{"date": "2017-03-22T08:55:00Z", "value": "294"}, {"date": "2017-06-26T06:40:00Z", "value": "330"}, {"date": "2017-08-15T13:23:00Z", "value": "337"}, {"date": "2017-11-20T12:06:00Z", "value": "365"}, {"date": "2018-02-02T16:15:00Z", "value": "387"}, {"date": "2018-03-14T11:58:00Z", "value": "295"}, {"date": "2018-04-11T11:06:00Z", "value": "296"}, {"date": "2018-05-24T07:14:00Z", "value": "341"}, {"date": "2018-05-30T15:11:00Z", "value": "331"}, {"date": "2018-07-25T12:46:00Z", "value": "316"}], "units": null}